numpy_groupies/__init__.py
numpy_groupies/_version.py
numpy_groupies/aggregate_numba.py
numpy_groupies/aggregate_numpy.py
numpy_groupies/aggregate_numpy_ufunc.py
numpy_groupies/aggregate_pandas.py
numpy_groupies/aggregate_purepy.py
numpy_groupies/utils.py
numpy_groupies/benchmarks/__init__.py
numpy_groupies/benchmarks/generic.py
numpy_groupies/benchmarks/simple.py
numpy_groupies/tests/__init__.py
numpy_groupies/tests/test_compare.py
numpy_groupies/tests/test_generic.py
numpy_groupies/tests/test_indices.py
numpy_groupies/tests/test_utils.py
numpy_groupies-0.11.2.dist-info/LICENSE.txt
numpy_groupies-0.11.2.dist-info/METADATA
numpy_groupies-0.11.2.dist-info/WHEEL
numpy_groupies-0.11.2.dist-info/top_level.txt
numpy_groupies-0.11.2.dist-info/RECORD
