Metadata-Version: 2.1
Name: numpy-groupies
Version: 0.11.2
Summary: Optimised tools for group-indexing operations: aggregated sum and more.
Author-email: Michael Löffler <ml@occam.com.ua>, Daniel Manson <danielmanson.uk@gmail.com>
Maintainer-email: Deepak Cherian <dcherian@ucar.edu>
License: Copyright (c) 2016, numpy-groupies developers
Project-URL: source, https://github.com/ml31415/numpy-groupies
Project-URL: tracker, https://github.com/ml31415/numpy-groupies/issues
Keywords: accumarray,aggregate,groupby,grouping,indexing
Classifier: Development Status :: 4 - Beta
Classifier: Intended Audience :: Science/Research
Classifier: Intended Audience :: Developers
Classifier: Operating System :: OS Independent
Classifier: Programming Language :: Python :: 3
Classifier: Programming Language :: Python :: 3.9
Classifier: Programming Language :: Python :: 3.10
Classifier: Programming Language :: Python :: 3.11
Classifier: Programming Language :: Python :: 3.12
Classifier: Topic :: Scientific/Engineering
Classifier: Topic :: Software Development :: Libraries
Classifier: License :: OSI Approved :: BSD License
Requires-Python: >=3.9
License-File: LICENSE.txt
Requires-Dist: numpy
Provides-Extra: dev
Requires-Dist: pytest ; extra == 'dev'
Requires-Dist: numba ; extra == 'dev'
Requires-Dist: pandas ; extra == 'dev'
Provides-Extra: fast
Requires-Dist: numba ; extra == 'fast'
